odoo/addons/stock_procurement_customer/README.rst
odoo/addons/stock_procurement_customer/__init__.py
odoo/addons/stock_procurement_customer/__manifest__.py
odoo/addons/stock_procurement_customer/i18n/es.po
odoo/addons/stock_procurement_customer/i18n/it.po
odoo/addons/stock_procurement_customer/i18n/stock_procurement_customer.pot
odoo/addons/stock_procurement_customer/models/__init__.py
odoo/addons/stock_procurement_customer/models/procurement_group.py
odoo/addons/stock_procurement_customer/models/stock_move.py
odoo/addons/stock_procurement_customer/models/stock_picking.py
odoo/addons/stock_procurement_customer/readme/CONTRIBUTORS.rst
odoo/addons/stock_procurement_customer/readme/DESCRIPTION.rst
odoo/addons/stock_procurement_customer/readme/USAGE.rst
odoo/addons/stock_procurement_customer/static/description/icon.png
odoo/addons/stock_procurement_customer/static/description/index.html
odoo/addons/stock_procurement_customer/tests/__init__.py
odoo/addons/stock_procurement_customer/tests/test_stock_procurement_customer.py
odoo/addons/stock_procurement_customer/views/procurement_group.xml
odoo/addons/stock_procurement_customer/views/stock_picking.xml
odoo_addon_stock_procurement_customer-16.0.1.0.1.6.dist-info/METADATA
odoo_addon_stock_procurement_customer-16.0.1.0.1.6.dist-info/WHEEL
odoo_addon_stock_procurement_customer-16.0.1.0.1.6.dist-info/top_level.txt
odoo_addon_stock_procurement_customer-16.0.1.0.1.6.dist-info/RECORD
